SimpleShape/Example.py
SimpleShape/SimpleShape.py
SimpleShape/__init__.py
SimpleShape-1.2.dist-info/License.txt
SimpleShape-1.2.dist-info/METADATA
SimpleShape-1.2.dist-info/WHEEL
SimpleShape-1.2.dist-info/top_level.txt
SimpleShape-1.2.dist-info/RECORD
