Metadata-Version: 2.1
Name: SimpleShape
Version: 1.2
Summary: A simple package for creating geometric objects and 
Author: Tilen Žel
Author-email: tilen.zel@gmail.com
License: MIT
Classifier: Programming Language :: Python :: 3
Classifier: License :: OSI Approved :: MIT License
Classifier: Operating System :: OS Independent
License-File: License.txt
